CHANGES.txt
COPYRIGHT.txt
LICENSE.txt
README.txt
setup.py
src/stxnext/__init__.py
src/stxnext.log.egg-info/PKG-INFO
src/stxnext.log.egg-info/SOURCES.txt
src/stxnext.log.egg-info/dependency_links.txt
src/stxnext.log.egg-info/namespace_packages.txt
src/stxnext.log.egg-info/not-zip-safe
src/stxnext.log.egg-info/requires.txt
src/stxnext.log.egg-info/top_level.txt
src/stxnext/log/__init__.py
src/stxnext/log/browser.py
src/stxnext/log/configure.zcml
src/stxnext/log/logger.py
src/stxnext/log/stxnext.log-configure.zcml