Metadata-Version: 1.0
Name: stxnext.log
Version: 0.1.1
Summary: This logger offers some conveniences that make easier of logging from python code and from ZPT templates.
Home-page: http://stxnext.pl/open-source/stxnext.log
Author: STX Next Sp. z o.o, Wojciech Lichota
Author-email: info@stxnext.pl, wojciech.lichota@stxnext.pl
License: Zope Public License, Version 2.1 (ZPL)
Keywords: python log logger
Platform: any
Classifier: Development Status :: 3 - Alpha
Classifier: Framework :: Zope2
Classifier: Framework :: Zope3
Classifier: Intended Audience :: Developers
Classifier: License :: OSI Approved :: Zope Public License
Classifier: Natural Language :: English
Classifier: Programming Language :: Python
Classifier: Topic :: System :: Logging
Classifier: Topic :: Software Development :: Libraries :: Python Modules
